README.md
setup.cfg
setup.py
ktorch/__init__.py
ktorch/callbacks.py
ktorch/metrics.py
ktorch/model.py
ktorch/numpy_backend.py
ktorch.egg-info/PKG-INFO
ktorch.egg-info/SOURCES.txt
ktorch.egg-info/dependency_links.txt
ktorch.egg-info/requires.txt
ktorch.egg-info/top_level.txt
tests/__init__.py
tests/unit_tests/__init__.py
tests/unit_tests/test_callbacks.py
tests/unit_tests/test_metrics.py
tests/unit_tests/test_model.py